tableconv/__init__.py
tableconv/__version__.py
tableconv/core.py
tableconv/exceptions.py
tableconv/in_memory_query.py
tableconv/interactive.py
tableconv/main.py
tableconv/parameter_parsing_utils.py
tableconv/parse_time.py
tableconv/uri.py
tableconv/adapters/__init__.py
tableconv/adapters/df/__init__.py
tableconv/adapters/df/ascii.py
tableconv/adapters/df/avro.py
tableconv/adapters/df/aws_athena.py
tableconv/adapters/df/aws_dynamodb.py
tableconv/adapters/df/aws_logs.py
tableconv/adapters/df/base.py
tableconv/adapters/df/duckdb.py
tableconv/adapters/df/dzn.py
tableconv/adapters/df/example.py
tableconv/adapters/df/file_adapter_mixin.py
tableconv/adapters/df/gsheets.py
tableconv/adapters/df/iceberg.py
tableconv/adapters/df/jc.py
tableconv/adapters/df/jira.py
tableconv/adapters/df/json.py
tableconv/adapters/df/leveldb.py
tableconv/adapters/df/nested_list.py
tableconv/adapters/df/numbers.py
tableconv/adapters/df/osquery.py
tableconv/adapters/df/pandas_io.py
tableconv/adapters/df/pcap.py
tableconv/adapters/df/protobuf.py
tableconv/adapters/df/python.py
tableconv/adapters/df/rdbms.py
tableconv/adapters/df/smart_sheet.py
tableconv/adapters/df/sql_literal.py
tableconv/adapters/df/sumo_logic.py
tableconv/adapters/df/text_array.py
tableconv/adapters/df/yaml.py
tableconv_daemon/__init__.py
tableconv_daemon/main.py
tableconv-1.9998.20260130.dist-info/METADATA
tableconv-1.9998.20260130.dist-info/WHEEL
tableconv-1.9998.20260130.dist-info/entry_points.txt
tableconv-1.9998.20260130.dist-info/licenses/LICENSE
tableconv-1.9998.20260130.dist-info/RECORD
