Metadata-Version: 2.4
Name: tableconv
Version: 1.9998.20260130
Summary: CLI data plumbing tool
Project-URL: Homepage, https://github.com/personalcomputer/tableconv
Author-email: John Miller <john@johngm.com>
License-File: LICENSE
Classifier: License :: OSI Approved :: MIT License
Classifier: Programming Language :: Python
Classifier: Programming Language :: Python :: 3
Classifier: Programming Language :: Python :: Implementation :: CPython
Requires-Python: >=3.11
Requires-Dist: aiohttp>=3.11.18
Requires-Dist: beautifulsoup4>=4.13.4
Requires-Dist: black>=25.1.0
Requires-Dist: boto3~=1.36.26
Requires-Dist: dpkt~=1.9.8
Requires-Dist: duckdb~=1.2.0
Requires-Dist: fastavro>=1.10.0
Requires-Dist: fastparquet~=2024.11.0
Requires-Dist: fsspec~=2025.2.0
Requires-Dist: genson~=1.3.0
Requires-Dist: google-api-python-client~=2.161.0
Requires-Dist: html5lib>=1.1
Requires-Dist: httplib2~=0.22.0
Requires-Dist: iso8601~=2.1.0
Requires-Dist: jc>=1.25.4
Requires-Dist: lxml~=5.3.1
Requires-Dist: marko~=2.1.2
Requires-Dist: msgpack>=1.1.0
Requires-Dist: oauth2client~=4.1.3
Requires-Dist: openpyxl~=3.1.5
Requires-Dist: osquery>=3.1.1
Requires-Dist: pandas~=2.2.3
Requires-Dist: pexpect~=4.9.0
Requires-Dist: psycopg2-binary~=2.9.10
Requires-Dist: pymysql~=1.1.1
Requires-Dist: python-dateutil~=2.9.0.post0
Requires-Dist: pyyaml~=6.0.2
Requires-Dist: remarshal>=1.0.0
Requires-Dist: rich>=13.9.4
Requires-Dist: sqlalchemy~=2.0.38
Requires-Dist: tables~=3.10.2
Requires-Dist: tabulate~=0.9.0
Requires-Dist: xlrd~=2.0.1
Requires-Dist: xlsxwriter~=3.2.2
Requires-Dist: xlwt~=1.3.0
Provides-Extra: full
Requires-Dist: leveldb-export; extra == 'full'
Requires-Dist: pyarrow>=20.0.0; extra == 'full'
Requires-Dist: pyiceberg>=0.9.1; extra == 'full'
